whw/__init__.py
whw/infos_wallet/__init__.py
whw/infos_wallet/config.py
whw/infos_wallet/infos.py
whw/security/__init__.py
whw/security/config.py
whw/security/security.py
whw/tokens/__init__.py
whw/tokens/contract.py
whw/tokens/tokens.py
whw/tokens/utils.py
whw/transaction/__init__.py
whw/transaction/mdl_transaction.py
whw/transaction/transaction.py
whw/wallet/__init__.py
whw/wallet/utils.py
whw/wallet/wallet.py
whw/wallet/wallet_eth.py
whw-0.1.1.dist-info/LICENSE
whw-0.1.1.dist-info/METADATA
whw-0.1.1.dist-info/WHEEL
whw-0.1.1.dist-info/top_level.txt
whw-0.1.1.dist-info/RECORD
