Metadata-Version: 2.1
Name: whw
Version: 0.1.1
Summary: Module gestion wallet basé sur la blockchain Ethereum
Home-page: https://gitlab.com/paquito3/whw-wallet-web3-module.git
Author: paquitoKikakop
Author-email: paquitokikakop@gmail.com
Classifier: Programming Language :: Python :: 3
Classifier: License :: OSI Approved :: MIT License
Classifier: Operating System :: OS Independent
Requires-Python: >=3.6
License-File: LICENSE
Requires-Dist: web3
Requires-Dist: cryptography
Requires-Dist: requests
